MANIFEST.in
README.rst
setup.cfg
setup.py
PhytoSFDM.egg-info/PKG-INFO
PhytoSFDM.egg-info/SOURCES.txt
PhytoSFDM.egg-info/dependency_links.txt
PhytoSFDM.egg-info/entry_points.txt
PhytoSFDM.egg-info/requires.txt
PhytoSFDM.egg-info/top_level.txt
phytosfdm/__init__.py
phytosfdm/EnvForcing/__init__.py
phytosfdm/EnvForcing/envforcing.py
phytosfdm/EnvForcing/mld_vd_WOA_Monterey_and_Levitus.nc
phytosfdm/EnvForcing/n0x_WOA09.nc
phytosfdm/EnvForcing/par_MODIS_2002to2011.nc
phytosfdm/EnvForcing/sst-t_an-WOA09.nc
phytosfdm/Example/__init__.py
phytosfdm/Example/__main__.py
phytosfdm/Example/example.py
phytosfdm/SizeModels/__init__.py
phytosfdm/SizeModels/sizemodels.py