Metadata-Version: 1.1
Name: PhytoSFDM
Version: 1.0.1
Summary: PhytoSFDM is a modelling framework to quantify phytoplankton community structure and functional diversity
Home-page: UNKNOWN
Author: Esteban Acevedo-Trejos
Author-email: esteban.acevedo@zmt-bremen.de
License: GPLv2
Platform: UNKNOWN
Classifier: Development Status :: 5 - Production/Stable
Classifier: Intended Audience :: Education
Classifier: Intended Audience :: Science/Research
Classifier: License :: OSI Approved :: GNU General Public License v2 (GPLv2)
Classifier: Natural Language :: English
Classifier: Programming Language :: Python
Classifier: Topic :: Education
Classifier: Topic :: Scientific/Engineering
